README.md
setup.py
ghviztoggle/__init__.py
ghviztoggle/__main__.py
ghviztoggle/cli.py
ghviztoggle/utils.py
ghviztoggle.egg-info/PKG-INFO
ghviztoggle.egg-info/SOURCES.txt
ghviztoggle.egg-info/dependency_links.txt
ghviztoggle.egg-info/requires.txt
ghviztoggle.egg-info/top_level.txt